mtb/__init__.py
mtb/log/__init__.py
mtb/log/emoji.py
mtb/log/fonts.py
mtb/log/list.py
mtb/log/logger.py
mtb/log/plot.py
mtb/log/title.py
mtb_log-0.5.0.dist-info/WHEEL
mtb_log-0.5.0.dist-info/METADATA
mtb_log-0.5.0.dist-info/RECORD
