Metadata-Version: 2.1
Name: mtb-log
Version: 0.5.0
Summary: Logging utilities
License: GPL-3.0-only
Keywords: logging,logging utilities
Author: Mel Massadian
Author-email: melmassadian@gmail.com
Maintainer: Mel Massadian
Maintainer-email: melmassadian@gmail.com
Requires-Python: >=3.6.2,<3.10
Classifier: Development Status :: 4 - Beta
Classifier: Intended Audience :: Developers
Classifier: License :: OSI Approved :: GNU General Public License v3 (GPLv3)
Classifier: Programming Language :: Python :: 3
Classifier: Programming Language :: Python :: 3.7
Classifier: Programming Language :: Python :: 3.8
Classifier: Programming Language :: Python :: 3.9
